sas_oda/__init__.py
sas_oda/sas_oda.py
sas_oda-1.0.0.dist-info/METADATA
sas_oda-1.0.0.dist-info/WHEEL
sas_oda-1.0.0.dist-info/top_level.txt
sas_oda-1.0.0.dist-info/RECORD
